cyberfusion/SecurityTXTPolicyServer/__init__.py
cyberfusion/SecurityTXTPolicyServer/database.py
cyberfusion/SecurityTXTPolicyServer/endpoints.py
cyberfusion/SecurityTXTPolicyServer/middleware.py
cyberfusion/SecurityTXTPolicyServer/server.py
cyberfusion/SecurityTXTPolicyServer/settings.py
cyberfusion/SecurityTXTPolicyServer/utilities.py
cyberfusion/SecurityTXTPolicyServer/exceptions/__init__.py
cyberfusion/SecurityTXTPolicyServer/exceptions/database.py
cyberfusion/SecurityTXTPolicyServer/exceptions/http_host_header.py
python3_cyberfusion_security_txt_policy_server-1.1.dist-info/METADATA
python3_cyberfusion_security_txt_policy_server-1.1.dist-info/WHEEL
python3_cyberfusion_security_txt_policy_server-1.1.dist-info/entry_points.txt
python3_cyberfusion_security_txt_policy_server-1.1.dist-info/top_level.txt
python3_cyberfusion_security_txt_policy_server-1.1.dist-info/RECORD
