Metadata-Version: 2.4
Name: python3-cyberfusion-security-txt-policy-server
Version: 1.1
Summary: security-txt-policy-server serves `.well-known/security.txt` files.
Author-email: Cyberfusion <support@cyberfusion.io>
Project-URL: Source, https://github.com/CyberfusionIO/python3-cyberfusion-security-txt-policy-server
Requires-Dist: starlette==0.46.1
Requires-Dist: uvicorn==0.32.0
Requires-Dist: validators==0.20.0
